diazo/__init__.py
diazo/annotate-rules.xsl
diazo/annotate-themes.xsl
diazo/apply-conditions.xsl
diazo/apply-rules.xsl
diazo/compiler.py
diazo/cssrules.py
diazo/defaults.xsl
diazo/diazo-debug.zcml
diazo/dummy.html
diazo/emit-stylesheet.xsl
diazo/filter.xsl
diazo/filter_html.xsl
diazo/filter_xhtml.xsl
diazo/fixup-themes.xsl
diazo/identity.xsl
diazo/include.xsl
diazo/merge-conditions.xsl
diazo/normalize-rules.xsl
diazo/rules.py
diazo/run.py
diazo/runtrace.py
diazo/runtrace_to_html.xsl
diazo/update-namespace.xsl
diazo/utils.py
diazo/wsgi.py
diazo/debug_resources/diazo-debug.css
diazo/debug_resources/diazo-debug.js
diazo/debug_resources/iframe.js
diazo/debug_resources/jquery-1.8.3.min.js
diazo/tests/__init__.py
diazo/tests/default-options.cfg
diazo/tests/test_diazo.py
diazo/tests/test_trace.py
diazo/tests/test_wsgi.py
diazo/tests/absolute-prefix/content.html
diazo/tests/absolute-prefix/options.cfg
diazo/tests/absolute-prefix/output.html
diazo/tests/absolute-prefix/rules.xml
diazo/tests/absolute-prefix/theme.html
diazo/tests/absolute-prefix-disabled/content.html
diazo/tests/absolute-prefix-disabled/options.cfg
diazo/tests/absolute-prefix-disabled/output.html
diazo/tests/absolute-prefix-disabled/rules.xml
diazo/tests/absolute-prefix-disabled/theme.html
diazo/tests/absolute-prefix-ie-conditional-comments/content.html
diazo/tests/absolute-prefix-ie-conditional-comments/options.cfg
diazo/tests/absolute-prefix-ie-conditional-comments/output.html
diazo/tests/absolute-prefix-ie-conditional-comments/rules.xml
diazo/tests/absolute-prefix-ie-conditional-comments/theme.html
diazo/tests/allow-curly-brackets/README.rst
diazo/tests/allow-curly-brackets/content.html
diazo/tests/allow-curly-brackets/output.html
diazo/tests/allow-curly-brackets/rules.xml
diazo/tests/allow-curly-brackets/theme.html
diazo/tests/append/content.html
diazo/tests/append/output.html
diazo/tests/append/rules.xml
diazo/tests/append/theme.html
diazo/tests/append/xpaths.txt
diazo-2.0.4.dist-info/licenses/LICENSE.txt
diazo-2.0.4.dist-info/METADATA
diazo-2.0.4.dist-info/WHEEL
diazo-2.0.4.dist-info/entry_points.txt
diazo-2.0.4.dist-info/top_level.txt
diazo-2.0.4.dist-info/RECORD
