Metadata-Version: 2.4
Name: diazo
Version: 2.0.4
Summary: Diazo implements a Deliverance like language using a pure
Home-page: http://diazo.org
Author: Paul Everitt, Laurence Rowe and Martin Aspeli.
Author-email: laurence@lrowe.co.uk
License: New BSD
Keywords: web theming
Classifier: Development Status :: 6 - Mature
Classifier: License :: OSI Approved :: BSD License
Classifier: Programming Language :: Python
Classifier: Programming Language :: Python :: 3.8
Classifier: Programming Language :: Python :: 3.9
Classifier: Programming Language :: Python :: 3.10
Classifier: Programming Language :: Python :: 3.11
Classifier: Programming Language :: Python :: 3.12
Classifier: Topic :: Internet :: WWW/HTTP
Classifier: Topic :: Internet :: WWW/HTTP :: WSGI
Classifier: Topic :: Internet :: WWW/HTTP :: WSGI :: Middleware
Classifier: Topic :: Text Processing :: Markup :: XML
Requires-Python: >=3.8
License-File: LICENSE.txt
Requires-Dist: lxml
Requires-Dist: cssselect
Provides-Extra: wsgi
Requires-Dist: repoze.xmliter; extra == "wsgi"
Requires-Dist: WebOb; extra == "wsgi"
Provides-Extra: test
Requires-Dist: repoze.xmliter; extra == "test"
Requires-Dist: WebOb; extra == "test"
Dynamic: author
Dynamic: author-email
Dynamic: classifier
Dynamic: description
Dynamic: home-page
Dynamic: keywords
Dynamic: license
Dynamic: license-file
Dynamic: provides-extra
Dynamic: requires-dist
Dynamic: requires-python
Dynamic: summary
